latex_render/__init__.py
latex_render/__main__.py
latex_render/render.py
latex_render/version.py
latex_render-0.0.1.dist-info/METADATA
latex_render-0.0.1.dist-info/WHEEL
latex_render-0.0.1.dist-info/entry_points.txt
latex_render-0.0.1.dist-info/top_level.txt
latex_render-0.0.1.dist-info/RECORD
