Metadata-Version: 2.1
Name: latex-render
Version: 0.0.1
Summary: latex_render for markdown
Home-page: https://github.com/bo-ke/latex_render
Author: kebo
Author-email: kebo0912@outlook.com
License: UNKNOWN
Platform: UNKNOWN
Requires-Python: >=3.6.1
Requires-Dist: typing (~=3.6.4)
Requires-Dist: overrides (~=2.8.0)
